[
	{
		"textOne": "все ошибки в проекте",
		"accentOne": "javascript-react",
		"textTwo": "в виде таблицы"
	},
	{
		"textOne": "список событий проекта",
		"accentOne": "javascript-react"
	},
	{
		"textOne": "найди список событий проблемы",
		"accentOne": "4150374871"
	},
	{
		"textOne": "список хешей проблемы",
		"accentOne": "4150374871"
	},
	{
		"textOne": "сведения о теге",
		"accentOne": "browser",
		"textTwo": "в ошибке",
		"accentTwo": "4150374871"
	},
	{
		"textOne": "покажи событие",
		"accentOne": "9999aaaaca8b46d797c23c6077c6ff01",
		"textTwo": "в проекте",
		"accentTwo": "javascript-react"
	},
	{
		"textOne": "найди последнее событе для проблемы",
		"accentOne": "4150374871"
	}
]